{
  "guid": "21EC2020-3AEA-4069-A2DD-08002B30309D",
  "updatedOn": "2016-10-13 18:49:34.589",
  "configuration": [
    {
      "shutdownHours": 120,
      "volume": [
        {
          "startTime": "07:30",
          "level": 50
        }
      ],
      "evergreen":[
        {
          "filename": "CNN04028_HLNSAT.webm",
          "expiryHours": 25,
          "swapFilename": "CNN04031_HLNSWAP.webm"
        },
        {
          "filename": "CNN04029_HLNSUN.webm",
          "expiryHours": 25,
          "swapFilename": "CNN04031_HLNSWAP.webm"
        },
        {
          "filename": "CNN04104_HLNWEEKDAY.webm",
          "expiryHours": 25,
          "swapFilename": "CNN04031_HLNSWAP.webm"
        },
        {
          "filename": "GSTV.BO__.gstvbos.webm",
          "expiryHours": 25,
          "swapFilename": ""
        },
        {
          "filename": "GSTV.DT__.gstvdtw.webm",
          "expiryHours": 15,
          "swapFilename": "GTV12953_BUMPERCONNECT_GREEN.webm"
        },
        {
          "filename": "GSTV.DT__.gstvdtw.webm",
          "expiryHours": 15,
          "swapFilename": "GTV12953_BUMPERCONNECT_GREEN.webm"
        },
        {
          "filename": "GSTV.NATL.BLB03827_FINANCIALNEWS.webm",
          "expiryHours": 17,
          "swapFilename": "BLB03828_BLOOMSWAP.webm"
        },
        {
          "filename": "GSTV.NATL.CNN04028_HLNSAT.webm",
          "expiryHours": 25,
          "swapFilename": "CNN04031_HLNSWAP.webm"
        },
        {
          "filename": "GSTV.NATL.CNN04029_HLNSUN.webm",
          "expiryHours": 25,
          "swapFilename": "CNN04031_HLNSWAP.webm"
        },
        {
          "filename": "GSTV.NATL.CNN04030_SHOWBIZ.webm",
          "expiryHours": 37,
          "swapFilename": "CNN04032_SHOWBIZSWAP.webm"
        },
        {
          "filename": "GSTV.NATL.CNN04104_HLNWEEKDAY.webm",
          "expiryHours": 25,
          "swapFilename": "CNN04031_HLNSWAP.webm"
        },
        {
          "filename": "GSTV.NATL.ESN04791_GSTVESPN.webm",
          "expiryHours": 25,
          "swapFilename": "ESN04853_GSTVESPNSWAP.webm"
        },
        {
          "filename": "GSTV.NATL.HD_BLB03827_FINANCIALNEWS.webm",
          "expiryHours": 17,
          "swapFilename": "HD_BLB03828_BLOOMSWAP.webm"
        },
        {
          "filename": "GSTV.NATL.HD_ESN04791_GSTVESPN.webm",
          "expiryHours": 25,
          "swapFilename": "HD_ESN04853_GSTVESPNSWAP.webm"
        },
        {
          "filename": "GSTV.NATL.HD_ESN13797_DEPORTESFUTBOLFORD052015.webm",
          "expiryHours": 75,
          "swapFilename": ""
        },
        {
          "filename": "GSTV.NATL.HD_ESN13824_ESPNHISPANICSOCCER.webm",
          "expiryHours": 75,
          "swapFilename": "HD_ESN04853_GSTVESPNSWAP.webm"
        },
        {
          "filename": "gstvbos.webm",
          "expiryHours": 25,
          "swapFilename": "HD_GTV12953_BUMPERCONNECT_GREEN.webm"
        },
        {
          "filename": "gstvdtw.webm",
          "expiryHours": 15,
          "swapFilename": "GTV12953_BUMPERCONNECT_GREEN.webm"
        },
        {
          "filename": "HD_ESN13797_DEPORTESFUTBOLFORD052015.webm",
          "expiryHours": 75,
          "swapFilename": "HD_ESN04853_GSTVESPNSWAP.webm"
        },
        {
          "filename": "HD_ESN13824_ESPNHISPANICSOCCER.webm",
          "expiryHours": 75,
          "swapFilename": "HD_ESN04853_GSTVESPNSWAP.webm"
        },
        {
          "filename": "HD_gstvben.webm",
          "expiryHours": 15,
          "swapFilename": "HD_GTV12953_BUMPERCONNECT_GREEN.webm"
        },
        {
          "filename": "HD_rgstvr10.webm",
          "expiryHours": 24,
          "swapFilename": "GTV12953_BUMPERCONNECT_GREEN.webm"
        }
      ]
    }
  ]
}
